odoo/addons/sale_product_multi_add/README.rst
odoo/addons/sale_product_multi_add/__init__.py
odoo/addons/sale_product_multi_add/__manifest__.py
odoo/addons/sale_product_multi_add/i18n/de.po
odoo/addons/sale_product_multi_add/i18n/fr_FR.po
odoo/addons/sale_product_multi_add/i18n/sale_product_multi_add.pot
odoo/addons/sale_product_multi_add/readme/CONTRIBUTORS.rst
odoo/addons/sale_product_multi_add/readme/DESCRIPTION.rst
odoo/addons/sale_product_multi_add/readme/USAGE.rst
odoo/addons/sale_product_multi_add/static/description/icon.png
odoo/addons/sale_product_multi_add/static/description/index.html
odoo/addons/sale_product_multi_add/static/description/sale_product_multi_add.png
odoo/addons/sale_product_multi_add/tests/__init__.py
odoo/addons/sale_product_multi_add/tests/test_sale.py
odoo/addons/sale_product_multi_add/views/sale_view.xml
odoo/addons/sale_product_multi_add/wizards/__init__.py
odoo/addons/sale_product_multi_add/wizards/sale_import_products.py
odoo/addons/sale_product_multi_add/wizards/sale_import_products_view.xml
odoo11_addon_sale_product_multi_add-11.0.1.0.1.dist-info/METADATA
odoo11_addon_sale_product_multi_add-11.0.1.0.1.dist-info/WHEEL
odoo11_addon_sale_product_multi_add-11.0.1.0.1.dist-info/top_level.txt
odoo11_addon_sale_product_multi_add-11.0.1.0.1.dist-info/RECORD
